lribeiro.cherrypy.templating.genshi-1.0-py3.4-nspkg.pth
lribeiro.cherrypy.templating.genshi-1.0.dist-info/WHEEL
lribeiro.cherrypy.templating.genshi-1.0.dist-info/top_level.txt
lribeiro.cherrypy.templating.genshi-1.0.dist-info/DESCRIPTION.rst
lribeiro.cherrypy.templating.genshi-1.0.dist-info/namespace_packages.txt
lribeiro.cherrypy.templating.genshi-1.0.dist-info/METADATA
lribeiro.cherrypy.templating.genshi-1.0.dist-info/metadata.json
lribeiro.cherrypy.templating.genshi-1.0.dist-info/RECORD
lribeiro/cherrypy/templating/genshi/loader.py
lribeiro/cherrypy/templating/genshi/__init__.py
lribeiro/cherrypy/templating/genshi/renderer.py
